{
  "contract_details": {
    "symbol": "ETH",
    "secType": "CRYPTO",
    "exchange": "PAXOS",
    "currency": "USD"
  },
  "instrument_timezone": "UTC",
  "date_range": {
    "start_year": 2022,
    "start_month": 1,
    "start_day": 1,
    "end_year": 2025,
    "end_month": 5,
    "end_day": 16
  },
  "api_settings": {
    "ibkr_port": 4002,
    "client_id": 10,
    "max_active_requests": 5,
    "inter_request_delay_seconds": 12,
    "use_rth": 0,
    "what_to_show": "AGGTRADES",
    "max_connect_retries": 5,
    "connect_retry_delay_seconds": 30,
    "max_request_retries": 3,
    "request_retry_delay_seconds": 10
  },

  "output": {
    "filename_template": "{symbol}_1min_{start_year}-{end_year}_utc.csv"
  }
}

